server.py
mseep_android_mcp-0.1.3.dist-info/licenses/LICENSE
mseep_android_mcp-0.1.3.dist-info/METADATA
mseep_android_mcp-0.1.3.dist-info/WHEEL
mseep_android_mcp-0.1.3.dist-info/entry_points.txt
mseep_android_mcp-0.1.3.dist-info/top_level.txt
mseep_android_mcp-0.1.3.dist-info/RECORD
