Metadata-Version: 2.4
Name: mseep-android-mcp
Version: 0.1.3
Summary: An MCP server for android automation
Author-email: mseep <support@skydeck.ai>
Requires-Python: >=3.11
License-File: LICENSE
Requires-Dist: mcp>=1.0.0
Requires-Dist: pure-python-adb>=0.3.0.dev0
Requires-Dist: PyYAML>=6.0
Requires-Dist: Pillow>=10.0.0
Provides-Extra: test
Requires-Dist: pytest>=8.0.0; extra == "test"
Requires-Dist: pytest-mock>=3.12.0; extra == "test"
Requires-Dist: pytest-cov>=4.0.0; extra == "test"
Dynamic: license-file
